{
    "header": {
        "title": "Tìm Người Ở Ghép, Tìm Nam Ở Ghép, Tìm Nữ Ở Ghép, Mới Nhất 2024",
        "description": "Tìm người ở ghép, tìm nam ở ghép, tìm nữ ở ghép, share phòng trọ, tìm chỗ ở ghép cùng, tìm bạn ở ghép, xin ở ghép mới nhất 2024. Đăng tin ở ghép hiệu quả, nhanh chóng nhất..."
    },
    "body": [
        {
            "images": [],
            "header": {
                "title": "Mình cần tìm bạn ở ghép tại Nhân Chính, Thanh Xuân, Hà Nội",
                "star": "2",
                "class": {
                    "content": "Chuyên mục: Tìm người ở ghép Quận Thanh Xuân",
                    "clasType": "Tìm người ở ghép Quận Thanh Xuân"
                },
                "address": "Địa chỉ: 55 Chính Kinh, Phường Nhân Chính, Quận Thanh Xuân, Hà Nội",
                "attributes": {
                    "prices": "1.5 triệu/tháng",
                    "acreage": "25m2",
                    "published": "Hôm nay",
                    "hashtag": "655520"
                }
            },
            "mainContent": {
                "header": "Thông tin mô tả",
                "content": [
                    "Tìm 1 nữ ở ghép tại 55 Chính Kinh, Nhân Chính, Thanh Xuân, Hà Nội",
                    "Phòng sạch sẽ, full điều hoà, nóng lạnh, ngay gần chân ga Thượng Đình và các điểm xe bus thuận tiện đi lại",
                    "Giá phòng: 2.5tr ( chưa chia đôi) ",
                    "Ib hoặc liên hệ số: 0363369444 để được hỗ trợ thêm",
                    " "
                ]
            },
            "overview": {
                "header": "Thông tin liên hệ",
                "content": [
                    {
                        "name": "Liên hệ:",
                        "content": "Thùy Linh"
                    },
                    {
                        "name": "Điện thoại:",
                        "content": "0363369444"
                    },
                    {
                        "name": "Zalo",
                        "content": "0363369444"
                    }
                ]
            }
        },
        {
            "images": [
                "https://pt123.cdn.static123.com/images/thumbs/900x600/fit/2023/06/07/3dc79eae-cf1b-46fc-811a-7c16c7f94ddd_1686136807.jpg",
                "https://pt123.cdn.static123.com/images/thumbs/900x600/fit/2023/06/07/31cc1716-172a-4f03-8e13-d62f6c4ad097_1686136755.jpg",
                "https://pt123.cdn.static123.com/images/thumbs/900x600/fit/2023/06/07/c49bf127-8f11-4cb3-9a75-ee014afd7810_1686136797.png",
                "https://pt123.cdn.static123.com/images/thumbs/900x600/fit/2023/06/07/12c2a7ae-0237-40ba-90ae-8a05e07bc8e2_1686136799.png",
                "https://pt123.cdn.static123.com/images/thumbs/900x600/fit/2023/06/07/5152760c-4a0a-4d0c-9cea-563d83172732_1686136800.png",
                "https://pt123.cdn.static123.com/images/thumbs/900x600/fit/2023/06/07/60523b06-ed2e-4def-bdf5-5598eeb8654b_1686136806.jpg",
                "https://pt123.cdn.static123.com/images/thumbs/900x600/fit/2023/06/07/ce83d1b1-ccff-48d5-b933-f3b2a2513d85_1686136807.jpg",
                "https://pt123.cdn.static123.com/images/thumbs/900x600/fit/2023/06/07/3dc79eae-cf1b-46fc-811a-7c16c7f94ddd_1686136807.jpg",
                "https://pt123.cdn.static123.com/images/thumbs/900x600/fit/2023/06/07/31cc1716-172a-4f03-8e13-d62f6c4ad097_1686136755.jpg"
            ],
            "header": {
                "title": "Ở ghép trọn gói 1tr cả để xe, điện nước sát trường Đại Học",
                "star": "2",
                "class": {
                    "content": "Chuyên mục: Tìm người ở ghép Quận 5",
                    "clasType": "Tìm người ở ghép Quận 5"
                },
                "address": "Địa chỉ: 338/18 an dương vương An Dương Vương, Phường 4, Quận 5, Hồ Chí Minh",
                "attributes": {
                    "prices": "1 triệu/tháng",
                    "acreage": "20m2",
                    "published": "Hôm nay",
                    "hashtag": "627225"
                }
            },
            "mainContent": {
                "header": "Thông tin mô tả",
                "content": [
                    "Ở ghép giường tầng tại 338/18 an dương vương p4,q5",
                    "Trọn gói 1tr3 ( khai trương tháng đầu 1tr )bao điện nước, giữ xe, wifi, máy lạnh , máy giặt, bếp từ, tủ lạnh, vệ sinh hằng ngày . Cách các trường đại học chỉ 200m ( đại học sư phạm , đại học Sài Gòn , KHTN…) các trường DH Kinh tế , y dược , kinh tế đối ngoại , tài nguyên môi trường chỉ hơn 1km ."
                ]
            },
            "overview": {
                "header": "Thông tin liên hệ",
                "content": [
                    {
                        "name": "Liên hệ:",
                        "content": "Hoàng Phúc"
                    },
                    {
                        "name": "Điện thoại:",
                        "content": "0931313570"
                    },
                    {
                        "name": "Zalo",
                        "content": "0931313570"
                    }
                ]
            }
        },
        {
            "images": [
                "https://pt123.cdn.static123.com/images/thumbs/900x600/fit/2020/04/29/e3ec072e-14b5-4ee7-a07e-bfc53a77eabd_1588131803.jpg",
                "https://pt123.cdn.static123.com/images/thumbs/900x600/fit/2020/04/29/98efff12-242f-4702-b375-13eeda7839a8_1588131798.jpg",
                "https://pt123.cdn.static123.com/images/thumbs/900x600/fit/2020/04/29/960899a1-be60-4d4d-856c-1d8ec3d44f6d_1588131799.jpg",
                "https://pt123.cdn.static123.com/images/thumbs/900x600/fit/2020/04/29/8faa917b-72c0-4a76-a926-8e812011db21_1588131800.jpg",
                "https://pt123.cdn.static123.com/images/thumbs/900x600/fit/2020/04/29/dbe4ad64-7fea-4e4c-a3a7-60f6f60bfd39_1588131801.jpg",
                "https://pt123.cdn.static123.com/images/thumbs/900x600/fit/2020/04/29/e3ec072e-14b5-4ee7-a07e-bfc53a77eabd_1588131803.jpg",
                "https://pt123.cdn.static123.com/images/thumbs/900x600/fit/2020/04/29/98efff12-242f-4702-b375-13eeda7839a8_1588131798.jpg"
            ],
            "header": {
                "title": "Hệ thống KTX Q7 trọn gói 900k: Máy lạnh, máy giặt, nước uống",
                "star": "2",
                "class": {
                    "content": "Chuyên mục: Tìm người ở ghép Quận 7",
                    "clasType": "Tìm người ở ghép Quận 7"
                },
                "address": "Địa chỉ: Hẻm 350 Đường Huỳnh Tấn Phát, Phường Bình Thuận, Quận 7, Hồ Chí Minh",
                "attributes": {
                    "prices": "700.000 đồng/tháng",
                    "acreage": "20m2",
                    "published": "Hôm nay",
                    "hashtag": "301747"
                }
            },
            "mainContent": {
                "header": "Thông tin mô tả",
                "content": [
                    "Homestay Hoàng Phúc - CAO CẤP - ĐẦY ĐỦ TIỆN NGHI - CHUẨN 2 SAO- Trọn gói chỉ 700k trong tháng 4 ( giá bình thường chỉ 900k ) đã bao gồm: tiền phòng, điện nước, máy giặt, giữ xe, máy lạnh,wifi, máy tắm nước nóng, nước uống, có nhà bếp và phòng khách, vệ sinh hàng ngày... ( Cam kết không phát sinh)",
                    "Chi phí sinh hoạt, ăn uống khu vực xung quanh cực dễ chịu, Ngay KCX Tan Thuan, Đại học Tài chính Marketing, Khu Phú Mỹ Hưng...tiện đi lại các quận trung tâm và quận 7.",
                    "Yêu cầu: người đi làm có lí lịch rõ ràng, công việc ổn định hoặc học sinh, sinh viên.",
                    "Địa chỉ: Hẻm 350 Huỳnh Tấn Phát q7 ( Cách khu chế xuất 500m)",
                    "———— Địa chỉ: Các chi nhánh q7————",
                    "Cs1: 34 đường 36 P. Tân Quy, Q7 (Cách Lotte Mart chỉ 400m )",
                    "Cs2: 1134/4 Huỳnh Tấn Phát, Q7( sau lưng Phú Mỹ Hưng )",
                    "Cs3: Hẻm 350 Huỳnh Tấn Phát,Q7 (Cách KCX Tan thuan, ĐH Tài Chính Marketing chỉ 500m)",
                    "Các chi nhánh quận khác:",
                    "Cs4: 233/11/6 Nguyễn Trãi, P2, Q5",
                    "Cs5: 84 Nguyễn tất thành Q4- cách đại học Luật 200m, đại học Nguyễn Tất Thành.",
                    "Cs6: Hẻm C4 đường Phạm Hùng Q8 (Gần siêu thị Satra) đến gọi mình ra đón"
                ]
            },
            "overview": {
                "header": "Thông tin liên hệ",
                "content": [
                    {
                        "name": "Liên hệ:",
                        "content": "Hoàng Phúc"
                    },
                    {
                        "name": "Điện thoại:",
                        "content": "0931313570"
                    },
                    {
                        "name": "Zalo",
                        "content": "0931313570"
                    }
                ]
            }
        },
        {
            "images": [
                "https://pt123.cdn.static123.com/images/thumbs/900x600/fit/2020/10/04/71365b8d-3924-48fb-822c-541cfd4def62_1601762976.jpg",
                "https://pt123.cdn.static123.com/images/thumbs/900x600/fit/2020/10/04/3f3986a3-ea40-461a-b199-6f0c49ebd23e_1601762977.jpg",
                "https://pt123.cdn.static123.com/images/thumbs/900x600/fit/2018/11/25/e4b6807f-19b9-4c8a-8ac7-e6a207f280a0_1543083723.jpg",
                "https://pt123.cdn.static123.com/images/thumbs/900x600/fit/2018/11/25/c64c30bc-2d6d-4fe5-a0a2-3636feaf4446_1543083701.jpg",
                "https://pt123.cdn.static123.com/images/thumbs/900x600/fit/2018/11/25/26ceccea-b61a-467c-84cc-c561d39b96e5_1543083705.jpg",
                "https://pt123.cdn.static123.com/images/thumbs/900x600/fit/2018/11/25/310b5928-8c1a-4849-bb2b-a7e84009b6ea_1543083716.jpg",
                "https://pt123.cdn.static123.com/images/thumbs/900x600/fit/2018/11/25/d32a5d58-236d-4d7f-9208-bb9455c4cde3_1543083727.jpg",
                "https://pt123.cdn.static123.com/images/thumbs/900x600/fit/2018/11/25/8beef0be-448f-4afd-bd6f-e43e5e8a05d4_1543083712.jpg",
                "https://pt123.cdn.static123.com/images/thumbs/900x600/fit/2018/11/25/a4306921-694c-475d-b6c2-c787ec16d9ec_1543083720.jpg",
                "https://pt123.cdn.static123.com/images/thumbs/900x600/fit/2018/11/25/04449df6-1174-48b7-950e-b128f711b1da_1543083730.jpg",
                "https://pt123.cdn.static123.com/images/thumbs/900x600/fit/2020/10/04/6b9bd3e2-91c9-49db-8f8d-9f8d8884600e_1601762975.jpg",
                "https://pt123.cdn.static123.com/images/thumbs/900x600/fit/2020/10/04/36b07df1-0e09-4f6f-84a8-a38ad850805a_1601762975.jpg",
                "https://pt123.cdn.static123.com/images/thumbs/900x600/fit/2020/10/04/71365b8d-3924-48fb-822c-541cfd4def62_1601762976.jpg",
                "https://pt123.cdn.static123.com/images/thumbs/900x600/fit/2020/10/04/3f3986a3-ea40-461a-b199-6f0c49ebd23e_1601762977.jpg"
            ],
            "header": {
                "title": "KTX Phạm Hùng có máy lạnh, máy nước nóng, máy giặt chỉ 600k",
                "star": "2",
                "class": {
                    "content": "Chuyên mục: Tìm người ở ghép Quận 8",
                    "clasType": "Tìm người ở ghép Quận 8"
                },
                "address": "Địa chỉ: Nhà sách Nguyễn văn cừ, đường Phạm Hùng, quận 8",
                "attributes": {
                    "prices": "700.000 đồng/tháng",
                    "acreage": "20m2",
                    "published": "Hôm nay",
                    "hashtag": "274173"
                }
            },
            "mainContent": {
                "header": "Thông tin mô tả",
                "content": [
                    "Homestay Hoàng Phúc - CAO CẤP - ĐẦY ĐỦ TIỆN NGHI - CHUẨN 2 SAO- Trọn gói chỉ 900 ngàn ( Tháng đầu giảm 200k ) đã bao gồm: tiền phòng, điện nước, máy giặt, giữ xe, máy lạnh, máy tắm nước nóng, nước uống... ( Cam kết không phát sinh).",
                    "Tiện ích :",
                    "- Tủ quần áo.",
                    "- Máy tắm nước nóng.",
                    "- Máy lạnh.",
                    "- Máy giặt.",
                    "- Nhà bếp tiện nghi đầy đủ dụng cụ.",
                    "- Nước uống miễn phí.",
                    "- Internet 72 Mbps.",
                    "- Phòng sinh hoạt, phòng khách, đọc sách tiện nghi.",
                    "- Máy tắm nước nóng.",
                    "- Sân phơi đồ rộng rãi, dàn phơi thông minh.",
                    "- Có camera an ninh,có bảo vệ.",
                    "- Có người dọn vệ sinh MIỄN PHÍ.",
                    "- Nhà vệ sinh với thiết bị cao cấp (vòi sen, lavabo,...), nước nóng lạnh.",
                    "- Giữ xe miễn phí.",
                    "Chi phí sinh hoạt, ăn uống khu vực xung quanh cực dễ chịu, gần siêu thị Satra, đại học công nghệ Sài Gòn...tiện đi lại các quận trung tâm và quận 7.",
                    "Yêu cầu: người đi làm có lí lịch rõ ràng, công việc ổn định hoặc học sinh, sinh viên.",
                    "Địa chỉ: cs1: Hẻm C4 đường Phạm Hùng- quận 8 (Gần Siêu thị Satra) . Bạn đến gọi mình ra đón.",
                    "Các chi nhánh khắp q4, q7, q8",
                    "Hình ảnh và thông tin đúng 100%.",
                    "️ Hotline: 09.31.31.35.70"
                ]
            },
            "overview": {
                "header": "Thông tin liên hệ",
                "content": [
                    {
                        "name": "Liên hệ:",
                        "content": "Hoàng Phúc"
                    },
                    {
                        "name": "Điện thoại:",
                        "content": "0931313570"
                    },
                    {
                        "name": "Zalo",
                        "content": "0931313570"
                    }
                ]
            }
        },
        {
            "images": [
                "https://pt123.cdn.static123.com/images/thumbs/900x600/fit/2020/01/28/a22c7bb6-f4e8-41dc-a981-c6307ec1f572_1580190895.jpg",
                "https://pt123.cdn.static123.com/images/thumbs/900x600/fit/2020/01/28/c1527aa4-f682-4407-adbf-afb6fc3a74c5_1580190856.jpg",
                "https://pt123.cdn.static123.com/images/thumbs/900x600/fit/2020/01/28/0bb48568-b59a-4531-aeec-22265531cab5_1580190856.jpg",
                "https://pt123.cdn.static123.com/images/thumbs/900x600/fit/2020/01/28/e3ba3413-5060-488e-9f08-9dca049dbe0e_1580190870.jpg",
                "https://pt123.cdn.static123.com/images/thumbs/900x600/fit/2020/01/28/4cb43772-f25d-43fc-b3f6-0e3fbb23d05b_1580190859.jpg",
                "https://pt123.cdn.static123.com/images/thumbs/900x600/fit/2020/01/28/1fc84e96-73c9-4014-939a-46c3b78fafb1_1580190860.jpg",
                "https://pt123.cdn.static123.com/images/thumbs/900x600/fit/2020/01/28/cb7e4c02-92ab-4f01-be3c-0f6851ffa14d_1580190869.jpg",
                "https://pt123.cdn.static123.com/images/thumbs/900x600/fit/2020/01/28/b444f9dd-9530-4e62-b105-0e61d9a4e08b_1580190882.jpg",
                "https://pt123.cdn.static123.com/images/thumbs/900x600/fit/2020/01/28/a22c7bb6-f4e8-41dc-a981-c6307ec1f572_1580190895.jpg",
                "https://pt123.cdn.static123.com/images/thumbs/900x600/fit/2020/01/28/c1527aa4-f682-4407-adbf-afb6fc3a74c5_1580190856.jpg"
            ],
            "header": {
                "title": "Homestay Hoàng Phúc:Giường tầng trọn gói 700k ngay Lotte Mart",
                "star": "2",
                "class": {
                    "content": "Chuyên mục: Tìm người ở ghép Quận 7",
                    "clasType": "Tìm người ở ghép Quận 7"
                },
                "address": "Địa chỉ: 436 Đường Nguyễn Thị Thập, Phường Tân Quy, Quận 7, Hồ Chí Minh",
                "attributes": {
                    "prices": "700.000 đồng/tháng",
                    "acreage": "25m2",
                    "published": "Hôm nay",
                    "hashtag": "294500"
                }
            },
            "mainContent": {
                "header": "Thông tin mô tả",
                "content": [
                    "Đến Homestay Hoàng Phúc – chuỗi kytucxa q7 rẻ nhất Sài Gòn – bạn sẽ được sống trong những căn phòng đẹp lung linh chuẩn 2 sao, đa dạng tiện ích và được sinh hoạt trong không gian ấm cúng như chính ở nhà.",
                    "Nhằm hỗ trợ tối ưu cho các sinh viên và người đi làm, hệ thống KTX Q7 chúng mình miễn phí toàn bộ các chi phí (cam kết 100% không phát sinh), các bạn chỉ cần vào ở với mức giá cố định 700.000 VNĐ/ tháng thôi nè!",
                    "Tiện ích cá nhân ở ký túc xá:",
                    "- Phòng giường tầng riêng tư, rộng rãi, có chăn ga gối nệm, tủ để đồ tại giường kèm hệ thống móc treo thông minh.",
                    "- Giá cố định trọn gói, miễn phí tiền điện nước và các chi phí bổ sung khác.",
                    "Tiện ích chung tại ký túc xá:",
                    "- Phòng ở mới tinh tươm, được decor siêu xinh và đầy đủ đồ dùng thiết yếu.",
                    "- Trang bị máy lạnh inventer, wifi tốc độ cao ở mỗi tầng.",
                    "- Có nhà vệ sinh riêng, được dọn dẹp vệ sinh phòng hằng ngày.",
                    "- Có phòng đọc sách, phòng sinh hoạt, phòng khách...rộng rãi và thoải mái.",
                    "- Máy giặt, máy nóng lạnh, bình lọc nước,… được sử dụng thả ga.",
                    "- Có nhà để xe rộng, bảo vệ kiểm tra tích hợp camera giám sát.",
                    "- Giờ giấc tự do, môi trường sống văn minh thân thiện.",
                    "- Khu nhà bếp đầy đủ tiện nghi, đồ dùng nấu nướng.",
                    "- Có sân phơi quần áo rộng kèm hệ thống phơi thông minh.",
                    "Tiện ích khu vực ký túc xá:",
                    "- Vị trí nằm ở trung tâm, thuận lợi di chuyển đến các quận 4, quận 8, quận 5, quận 1,… trong thời gian ngắn.",
                    "- Gần các trung tâm thương mại như siêu thị Lotte, siêu thị BigC, trường ĐH Tôn Đức Thắng, ĐH Tài Chính Marketing, KCX Tân Thuận,…",
                    "- Mức sống khu vực dễ chịu, dễ dàng đi lại và ăn uống.",
                    "Địa chỉ các cơ sở chi nhánh KTX:",
                    "CN1: 34 đường 36, P. Tân Quy, Q7 (Cách Lotte Mart chỉ 400m).",
                    "CN2: 1134/14A Huỳnh Tấn Phát, Q7 (sau lưng Phú Mỹ Hưng).",
                    "CN3: Hẻm 350 Huỳnh Tấn Phát, Q7 (Cách KCX Tân Thuận, cách ĐH Tài Chính Marketing chỉ 500m).",
                    "CN4: 233/11/6 Nguyễn Trãi, P2, Q5 gần KHTN, Đai học Sư Phạm.",
                    "CN5: 84 Nguyễn Tất Thành, Q4 - cách đại học Luật 200m, đại học Nguyễn Tất Thành 300m.",
                    "CN6: Hẻm C4 đường Phạm Hùng, Q8 (Gần siêu thị Satra).",
                    "Thông tin liên hệ tư vấn và xem phòng: qua hotline 0931313570 (gặp anh Phúc) hoặc có thể đến trực tiếp xem trực tiếp."
                ]
            },
            "overview": {
                "header": "Thông tin liên hệ",
                "content": [
                    {
                        "name": "Liên hệ:",
                        "content": "Hoàng Phúc"
                    },
                    {
                        "name": "Điện thoại:",
                        "content": "0931313570"
                    },
                    {
                        "name": "Zalo",
                        "content": "0931313570"
                    }
                ]
            }
        },
        {
            "images": [
                "https://pt123.cdn.static123.com/images/thumbs/900x600/fit/2020/01/28/2154e6bb-da4d-492c-b4d1-b5b060d52434_1580191245.jpg",
                "https://pt123.cdn.static123.com/images/thumbs/900x600/fit/2020/01/28/c21f890b-9acd-4fab-8e46-13d9341b0573_1580191219.jpg",
                "https://pt123.cdn.static123.com/images/thumbs/900x600/fit/2020/01/28/1ebd3721-0857-49f0-b673-86926e75fdcc_1580191218.jpg",
                "https://pt123.cdn.static123.com/images/thumbs/900x600/fit/2020/01/28/a0e1b188-0257-486f-a324-03f85ecae90f_1580191223.jpg",
                "https://pt123.cdn.static123.com/images/thumbs/900x600/fit/2020/01/28/331fa5fe-579f-48ca-9f91-97842db9c284_1580191230.jpg",
                "https://pt123.cdn.static123.com/images/thumbs/900x600/fit/2020/01/28/d89efa5d-fe1c-46b4-8087-0eb13c2bc9e4_1580191237.jpg",
                "https://pt123.cdn.static123.com/images/thumbs/900x600/fit/2020/01/28/41dbfe64-cb3f-4747-9c23-b66db462b94a_1580191239.jpg",
                "https://pt123.cdn.static123.com/images/thumbs/900x600/fit/2020/01/28/e8a877e1-9456-4f45-a6d3-001ca6e6595b_1580191243.jpg",
                "https://pt123.cdn.static123.com/images/thumbs/900x600/fit/2020/01/28/2154e6bb-da4d-492c-b4d1-b5b060d52434_1580191245.jpg",
                "https://pt123.cdn.static123.com/images/thumbs/900x600/fit/2020/01/28/c21f890b-9acd-4fab-8e46-13d9341b0573_1580191219.jpg"
            ],
            "header": {
                "title": "Ở ghép trọn gói 800k ngay cầu Khánh Hội",
                "star": "2",
                "class": {
                    "content": "Chuyên mục: Tìm người ở ghép Quận 4",
                    "clasType": "Tìm người ở ghép Quận 4"
                },
                "address": "Địa chỉ: 84 Đường Nguyễn Tất Thành, Phường 12, Quận 4, Hồ Chí Minh",
                "attributes": {
                    "prices": "800.000 đồng/tháng",
                    "acreage": "25m2",
                    "published": "Hôm nay",
                    "hashtag": "294501"
                }
            },
            "mainContent": {
                "header": "Thông tin mô tả",
                "content": [
                    "Homestay Hoàng Phúc - CAO CẤP - ĐẦY ĐỦ TIỆN NGHI - CHUẨN 2 SAO- Trọn gói chỉ 800k - các tháng sau chỉ từ 1tr đã bao gồm: tiền phòng, điện nước, máy giặt, giữ xe, máy lạnh,wifi, máy tắm nước nóng, nước uống... ( Cam kết không phát sinh).",
                    "Tiện ích :",
                    "- Giường tầng thoáng mát, rộng rãi.",
                    "- Tủ quần áo.",
                    "- Máy tắm nước nóng.",
                    "- Máy lạnh.",
                    "- Máy giặt.",
                    "- Nhà bếp tiện nghi đầy đủ dụng cụ.",
                    "- Nước uống miễn phí.",
                    "- Internet 72 Mbps.",
                    "- Phòng sinh hoạt, phòng khách, đọc sách tiện nghi.",
                    "- Máy tắm nước nóng.",
                    "- Sân phơi đồ rộng rãi, dàn phơi thông minh.",
                    "- Có camera an ninh,có bảo vệ.",
                    "- Có người dọn vệ sinh MIỄN PHÍ.",
                    "- Nhà vệ sinh với thiết bị cao cấp (vòi sen, lavabo,...), nước nóng lạnh.",
                    "- Giờ giấc tự do",
                    "- Giữ xe miễn phí.",
                    "Chi phí sinh hoạt, ăn uống khu vực xung quanh cực dễ chịu, gần siêu thị Coop mart, Ngay Phú Mỹ Hưng...tiện đi lại các quận trung tâm và quận 7.",
                    "Yêu cầu: người đi làm có lí lịch rõ ràng, công việc ổn định hoặc học sinh, sinh viên.",
                    "Địa chỉ: 84 Nguyễn Tất Thành p12 q4",
                    "———— Địa chỉ: Các chi nhánh q7————",
                    "Cs1: 34 đường 36 P. Tân Quy, Q7 (Cách Lotte Mart chỉ 400m )",
                    "Cs2: 1134/4 Huỳnh Tấn Phát, Q7( sau lưng Phú Mỹ Hưng )",
                    "Cs3: Hẻm 350 Huỳnh Tấn Phát,Q7 (Cách KCX Tan thuan, ĐH Tài Chính Marketing chỉ 500m)",
                    "Các chi nhánh quận khác:",
                    "Cs4: 233/11/6 Nguyễn Trãi, P2, Q5",
                    "Cs5: 84 Nguyễn tất thành Q4- cách đại học Luật 200m, đại học Nguyễn Tất Thành.",
                    "Cs6: Hẻm C4 đường Phạm Hùng Q8 (Gần siêu thị Satra) đến gọi mình ra đón",
                    "Hình ảnh và thông tin đúng 100%.",
                    "️ Hotline:"
                ]
            },
            "overview": {
                "header": "Thông tin liên hệ",
                "content": [
                    {
                        "name": "Liên hệ:",
                        "content": "Hoàng Phúc"
                    },
                    {
                        "name": "Điện thoại:",
                        "content": "0931313570"
                    },
                    {
                        "name": "Zalo",
                        "content": "0931313570"
                    }
                ]
            }
        },
        {
            "images": [
                "https://pt123.cdn.static123.com/images/thumbs/900x600/fit/2020/09/09/8c195b1c-1236-42a5-ad12-bbdf60d65286_1599588067.jpg",
                "https://pt123.cdn.static123.com/images/thumbs/900x600/fit/2020/09/09/f8d25335-2c11-4faa-83af-7fd04eb32227_1599588060.jpg",
                "https://pt123.cdn.static123.com/images/thumbs/900x600/fit/2020/09/09/ea92d131-ba75-4384-816e-be3539a422cb_1599588060.jpg",
                "https://pt123.cdn.static123.com/images/thumbs/900x600/fit/2020/09/09/c7b2e9f9-dac7-451a-b2d9-ba819d6c15dd_1599588061.jpg",
                "https://pt123.cdn.static123.com/images/thumbs/900x600/fit/2020/09/09/2f16dfe6-49a9-4b1b-8e36-30bf426117d6_1599588061.jpg",
                "https://pt123.cdn.static123.com/images/thumbs/900x600/fit/2020/09/09/d036f687-c76c-439f-9d64-308f98650337_1599588062.jpg",
                "https://pt123.cdn.static123.com/images/thumbs/900x600/fit/2020/09/09/db34745c-4c3d-4a2c-9eee-2c10523d3892_1599588066.jpg",
                "https://pt123.cdn.static123.com/images/thumbs/900x600/fit/2020/09/09/4a9d2ab4-a8ee-45b7-a70c-768fd5beeaa3_1599588063.jpg",
                "https://pt123.cdn.static123.com/images/thumbs/900x600/fit/2020/09/09/a03d622b-3076-433e-a9af-0e487e151757_1599588064.jpg",
                "https://pt123.cdn.static123.com/images/thumbs/900x600/fit/2020/09/09/cca30e26-d6d9-424d-866d-01398d03271a_1599588064.jpg",
                "https://pt123.cdn.static123.com/images/thumbs/900x600/fit/2020/09/09/4bebe380-b760-4d9d-9190-e7b0bcc3d363_1599588066.jpg",
                "https://pt123.cdn.static123.com/images/thumbs/900x600/fit/2020/09/09/8c195b1c-1236-42a5-ad12-bbdf60d65286_1599588067.jpg",
                "https://pt123.cdn.static123.com/images/thumbs/900x600/fit/2020/09/09/f8d25335-2c11-4faa-83af-7fd04eb32227_1599588060.jpg"
            ],
            "header": {
                "title": "Ở ghép gần Trường DH Luật và Nguyễn Tất Thành đầy đủ tiện nghi",
                "star": "2",
                "class": {
                    "content": "Chuyên mục: Tìm người ở ghép Quận 1",
                    "clasType": "Tìm người ở ghép Quận 1"
                },
                "address": "Địa chỉ: Phố Tôn Đức Thắng, Phường Bến Nghé, Quận 1, Hồ Chí Minh",
                "attributes": {
                    "prices": "800.000 đồng/tháng",
                    "acreage": "20m2",
                    "published": "Hôm nay",
                    "hashtag": "310536"
                }
            },
            "mainContent": {
                "header": "Thông tin mô tả",
                "content": [
                    "Đến Homestay Hoàng Phúc – hệ thống Kytucxa giá rẻ nhất Sài Gòn với những căn phòng đẹp lung linh chuẩn 2 sao, đa dạng tiện nghi và bao trọn toàn bộ các chi phí (cam kết 100% không phát sinh).",
                    "CHỈ 9️⃣0️⃣0️⃣.0️⃣0️⃣0️⃣/ THÁNG( KM 200K tháng đầu chị còn 7️⃣0️⃣0️⃣.0️⃣0️⃣0️⃣/ THÁNG )",
                    "TIỆN ÍCH NỔI TRỘI TẠI ĐÂY:",
                    "Giường tầng riêng tư, có tủ đồ, móc treo thông minh",
                    "️ ️Máy lạnh 24/7, wifi tốc độ cao",
                    "Nhà vệ sinh riêng, sạch sẽ",
                    "Nhân viên dọn phòng hằng ngày",
                    "Tự do dùng máy giặt, máy nóng lạnh, bình lọc nước",
                    "Khu để xe rộng, được camera giám sát.",
                    "⏰ ⏰ Giờ giấc tự do, môi trường văn minh",
                    "Ngoài ra còn có:",
                    "Camera An ninh, quản lý tâm huyết.",
                    "Không gian bếp lớn đầy đủ thiết bị.",
                    "Có khu phơi quần áo riêng.",
                    "Vị trí ở trung tâm, mức sống dễ chịu, thuận lợi đi lại và ăn uống và rất nhiều các chi nhánh để các chọn lựa gần chỗ làm nơi học.",
                    "Địa chỉ các cơ sở chi nhánh KTX:",
                    "️CN1: 84 Nguyễn Tất Thành P12 Q4",
                    "Các chi nhánh khác:",
                    "️CN2: 1134/14A Huỳnh Tấn Phát, Q.7",
                    "️CN3: Hẻm 350 Huỳnh Tấn Phát, Q.7",
                    "️CN4: 233/11/6 Nguyễn Trãi, P2, Q.5",
                    "️ CN5: 34 đường 36 P.Tân Quy, Q7",
                    "️CN6: Hẻm C4 Phạm Hùng Q8 ( đến gọi mình ra đón )",
                    "Phone : 0931313570 ( Phuc )",
                    "CÒN CHẦN CHỜ GÌ NỮA NHANH TAY LIÊN HỆ CHO MÌNH 1 CHỖ",
                    "#kytucxaq1 #ktxq1#homestayhoangphuc #nhatrogiare #oghepq1 #phongtrosinhvien"
                ]
            },
            "overview": {
                "header": "Thông tin liên hệ",
                "content": [
                    {
                        "name": "Liên hệ:",
                        "content": "Hoàng Phúc"
                    },
                    {
                        "name": "Điện thoại:",
                        "content": "0931313570"
                    },
                    {
                        "name": "Zalo",
                        "content": "0931313570"
                    }
                ]
            }
        },
        {
            "images": [
                "https://pt123.cdn.static123.com/images/thumbs/900x600/fit/2020/04/09/cua-chinh_1586437528.jpg",
                "https://pt123.cdn.static123.com/images/thumbs/900x600/fit/2019/10/13/phong-khach_1570975727.jpg",
                "https://pt123.cdn.static123.com/images/thumbs/900x600/fit/2019/10/13/nha-ve-sinh_1570975735.jpg",
                "https://pt123.cdn.static123.com/images/thumbs/900x600/fit/2020/04/09/hanh-lang_1586437519.jpg",
                "https://pt123.cdn.static123.com/images/thumbs/900x600/fit/2020/04/09/cua-chinh_1586437528.jpg",
                "https://pt123.cdn.static123.com/images/thumbs/900x600/fit/2019/10/13/phong-khach_1570975727.jpg"
            ],
            "header": {
                "title": "Cần 2 nhân viên nữ ở ghép, 1.5 triệu/tháng, căn hộ chung cư 60m2",
                "star": "2",
                "class": {
                    "content": "Chuyên mục: Tìm người ở ghép Quận 1",
                    "clasType": "Tìm người ở ghép Quận 1"
                },
                "address": "Địa chỉ: 189B C/c Đường Cống Quỳnh, Phường Nguyễn Cư Trinh, Quận 1, Hồ Chí Minh",
                "attributes": {
                    "prices": "1.5 triệu/tháng",
                    "acreage": "60m2",
                    "published": "Hôm nay",
                    "hashtag": "289474"
                }
            },
            "mainContent": {
                "header": "Thông tin mô tả",
                "content": [
                    "Cần 2 nhân viên văn phòng nữ ở ghép, giờ giấc tự do, chung cư 189B Cống Quỳnh, phường Nguyễn Cư Trinh, Quận 1",
                    "Giá thuê 1,5 tr/ tháng (chưa tính tiền điện nước), không cần thế chân.",
                    "Liên hệ: 0909888117 Hương",
                    " "
                ]
            },
            "overview": {
                "header": "Thông tin liên hệ",
                "content": [
                    {
                        "name": "Liên hệ:",
                        "content": "Hương Nguyễn"
                    },
                    {
                        "name": "Điện thoại:",
                        "content": "0909888117"
                    },
                    {
                        "name": "Zalo",
                        "content": "0909888117"
                    }
                ]
            }
        },
        {
            "images": [
                "https://pt123.cdn.static123.com/images/thumbs/900x600/fit/2024/05/26/img-2969_1716729959.jpg",
                "https://pt123.cdn.static123.com/images/thumbs/900x600/fit/2024/05/26/img-2969_1716729959.jpg"
            ],
            "header": {
                "title": "Cần tìm nam ở ghép , thật thà , dễ tính , tính kỹ lưỡng",
                "class": {
                    "content": "Chuyên mục: Tìm người ở ghép Quận Bình Thạnh",
                    "clasType": "Tìm người ở ghép Quận Bình Thạnh"
                },
                "address": "Địa chỉ: 235/30 Đường Đặng Thuỳ Trâm, Phường 13, Quận Bình Thạnh, Hồ Chí Minh",
                "attributes": {
                    "prices": "4.5 triệu/tháng",
                    "acreage": "19m2",
                    "published": "5 giờ trước",
                    "hashtag": "655787"
                }
            },
            "mainContent": {
                "header": "Thông tin mô tả",
                "content": [
                    "mình cần tìm 1 bạn nam ở ghép thật thà , dễ tính , kỹ lưỡng vì mình cũng ưu sạch sẽ , gọn gàng , dọn vào ở chung luôn , không cần đêm đồ j nhiều tại phòng mình đã có mua đầy đủ , nếu có mua chắc mua nước mắm , hạt nêm đồ thoi , và ĐẶT BIỆT : Do phòng mình cũng nhỏ nên diện tích chỉ có 1 chiếc giường nếu bạn khongo ngại thì mình rất sẵn lòng , đặt biệt có phòng có view công viên rất chill, giá cả ib mình : 0814757567 hoặc ib zalo"
                ]
            },
            "overview": {
                "header": "Thông tin liên hệ",
                "content": [
                    {
                        "name": "Liên hệ:",
                        "content": "Huỳnh hữu lộc"
                    },
                    {
                        "name": "Điện thoại:",
                        "content": "0814757567"
                    },
                    {
                        "name": "Zalo",
                        "content": "0814757567"
                    }
                ]
            }
        },
        {
            "images": [
                "https://pt123.cdn.static123.com/images/thumbs/900x600/fit/2024/03/12/img-20230418-110059_1710250100.jpg",
                "https://pt123.cdn.static123.com/images/thumbs/900x600/fit/2024/03/18/img-20230418-110050_1710731478.jpg",
                "https://pt123.cdn.static123.com/images/thumbs/900x600/fit/2024/03/12/img-20230822-144145_1710250097.jpg",
                "https://pt123.cdn.static123.com/images/thumbs/900x600/fit/2024/03/12/img-20230822-144154_1710250097.jpg",
                "https://pt123.cdn.static123.com/images/thumbs/900x600/fit/2024/03/12/img-20230822-144141_1710250098.jpg",
                "https://pt123.cdn.static123.com/images/thumbs/900x600/fit/2024/03/12/img-20230822-144143_1710250098.jpg",
                "https://pt123.cdn.static123.com/images/thumbs/900x600/fit/2024/03/12/img-20230822-144146_1710250099.jpg",
                "https://pt123.cdn.static123.com/images/thumbs/900x600/fit/2024/03/12/img-20230822-144240_1710250099.jpg",
                "https://pt123.cdn.static123.com/images/thumbs/900x600/fit/2024/03/12/img-20230418-110057_1710250099.jpg",
                "https://pt123.cdn.static123.com/images/thumbs/900x600/fit/2024/03/12/img-20230418-110056_1710250100.jpg",
                "https://pt123.cdn.static123.com/images/thumbs/900x600/fit/2024/03/12/img-20230418-110101_1710250100.jpg",
                "https://pt123.cdn.static123.com/images/thumbs/900x600/fit/2024/03/12/img-20230418-110059_1710250100.jpg",
                "https://pt123.cdn.static123.com/images/thumbs/900x600/fit/2024/03/18/img-20230418-110050_1710731478.jpg"
            ],
            "header": {
                "title": "KTX Chỉ 1tr7/Tháng.Bao Điện Nước CHO SV, NGƯỜI ĐI LÀM NGAY THẢO ĐIỀN Q2",
                "class": {
                    "content": "Chuyên mục: Tìm người ở ghép Quận 2",
                    "clasType": "Tìm người ở ghép Quận 2"
                },
                "address": "Địa chỉ: 21 Nguyễn Văn Hưởng, Phường Thảo Điền, Quận 2, Hồ Chí Minh",
                "attributes": {
                    "prices": "1.7 triệu/tháng",
                    "acreage": "120m2",
                    "published": "7 giờ trước",
                    "hashtag": "648776"
                }
            },
            "mainContent": {
                "header": "Thông tin mô tả",
                "content": [
                    "Phòng Ktx Ghép Máy Lạnh giá rẻ Tiện Nghi, Sạch đẹp - Ngay khu biệt thự Thảo Điền Q2..",
                    "- Giá thuê rẻ phù hợp với sinh viên,người đi làm,để tiết kiệm chi phí.",
                    "- Vị trí Ngay Trung tâm Thảo Điền,khu nhiều người nước ngoài sinh sống, Dân cư An Ninh,Cao Cấp,Sát bên,Chợ siêu thị Vincom..BigC..Masteri..Landmark 81.",
                    "- Cách cầu Sài Gòn 100m",
                    "- 5 phút ra VinCom, Maseteri",
                    "- 5 phút ra Landmark 81",
                    "- 5 phút ra ngã tư hành xanh",
                    "- 10 phút ra Quận 1,Quận 9,Quận 4, Thủ Đức",
                    "- 2 phút ra trường Đh Quốc Tế SG.Cao Dẳng Hàng Hải, ĐH Vẫn Hoá.",
                    "- Tiện ích xung quanh ,quán ăn,cafe,không thiếu gì",
                    "- Mọi thứ đã được trang bị đầy đủ. Các bạn chỉ cần xách vali vào ở thôi.",
                    "- Phòng Bao gồm nội thất",
                    "+ Máy Lạnh",
                    "+ Tủ lạnh",
                    "+ Tủ quần áo",
                    "+ Giường,nệm,ga, gối",
                    "+ Máy giặt",
                    "+ Bếp nấu",
                    "+ Sân phơi quần áo sạch đẹp",
                    "+ Wifi tốc độ cao",
                    "+ Bàn ghế làm việc",
                    "+ Xe để trong nhà miễn phí",
                    "+ Khóa Vân tay",
                    "+ Có camera an ninh 24/24",
                    "+ Giờ giấc tự đi lại tự do",
                    "+ Giá cho thuê chỉ: 1.7tr_1.9tr/tháng. Bao tất cả điện nước và dịch vụ quá rẻ luôn nhé.",
                    "@ ĐẶC BIỆT: có cho thuê theo ngày 100k/ngày Miễn phí tất cả dịch vụ nhé.",
                    "- Đc.Hẻm 215 Đường Nguyễn Văn Hưởng, Thảo Điền,Q2.Tp.Thủ Đức.",
                    "- Lh. Mr Luân xem phòng từ 8h sáng đến 22h hàng ngày.gọi trước 15 phút.",
                    "Cảm ơn các bạn đã đọc tin.!!"
                ]
            },
            "overview": {
                "header": "Thông tin liên hệ",
                "content": [
                    {
                        "name": "Liên hệ:",
                        "content": "Mr.Luan"
                    },
                    {
                        "name": "Điện thoại:",
                        "content": "0586999968"
                    },
                    {
                        "name": "Zalo",
                        "content": "0586999968"
                    }
                ]
            }
        },
        {
            "images": [
                "https://pt123.cdn.static123.com/images/thumbs/900x600/fit/2024/03/27/img-20240327-151427_1711527414.jpg",
                "https://pt123.cdn.static123.com/images/thumbs/900x600/fit/2024/03/09/img-20240309-161014_1709976841.jpg",
                "https://pt123.cdn.static123.com/images/thumbs/900x600/fit/2024/03/27/img-20240327-151531_1711527414.jpg",
                "https://pt123.cdn.static123.com/images/thumbs/900x600/fit/2024/03/27/img-20240327-151427_1711527414.jpg",
                "https://pt123.cdn.static123.com/images/thumbs/900x600/fit/2024/03/09/img-20240309-161014_1709976841.jpg"
            ],
            "header": {
                "title": "Cần bạn ở ghép thật thà , vui vẻ",
                "class": {
                    "content": "Chuyên mục: Tìm người ở ghép Quận Gò Vấp",
                    "clasType": "Tìm người ở ghép Quận Gò Vấp"
                },
                "address": "Địa chỉ: Đường Trần Bá Giao, Phường 5, Quận Gò Vấp, Hồ Chí Minh",
                "attributes": {
                    "prices": "1 triệu/tháng",
                    "acreage": "20m2",
                    "published": "10 giờ trước",
                    "hashtag": "648467"
                }
            },
            "mainContent": {
                "header": "Thông tin mô tả",
                "content": [
                    "mình cần bạn ở ghép share tiền phòng , 1 triệu/tháng , ưu tiên dân lao động hoặc shipper nhé ,mình đi làm chỉ tối về ngủ ,phòng giờ giấc tự do , an ninh tốt , phòng rộng rãi sạch sẽ , thoáng mát , cần bạn ở lâu dài ,"
                ]
            },
            "overview": {
                "header": "Thông tin liên hệ",
                "content": [
                    {
                        "name": "Liên hệ:",
                        "content": "Võ ngọc Trọng"
                    },
                    {
                        "name": "Điện thoại:",
                        "content": "0975585935"
                    },
                    {
                        "name": "Zalo",
                        "content": "0975585935"
                    }
                ]
            }
        },
        {
            "images": [
                "https://pt123.cdn.static123.com/images/thumbs/900x600/fit/2024/05/26/z5477035161099-551b78c6a3f0ea43a6bedb0cb4d06817_1716705678.jpg",
                "https://pt123.cdn.static123.com/images/thumbs/900x600/fit/2024/05/26/z5477018493225-b1d0074d0391e9dd076d0b0161d77904_1716705676.jpg",
                "https://pt123.cdn.static123.com/images/thumbs/900x600/fit/2024/05/26/z5477018495753-b11a69ce4f82e672edfa7a476fab3ea7_1716705676.jpg",
                "https://pt123.cdn.static123.com/images/thumbs/900x600/fit/2024/05/26/z5477018506088-fe487cf0e335b24abcd4ea00347a930d_1716705677.jpg",
                "https://pt123.cdn.static123.com/images/thumbs/900x600/fit/2024/05/26/z5477018514180-f0addef41afbb5988fbb00e2a600505b_1716705677.jpg",
                "https://pt123.cdn.static123.com/images/thumbs/900x600/fit/2024/05/26/z5477018518554-453bd825ecf639ac44205b17bd6eacf1_1716705677.jpg",
                "https://pt123.cdn.static123.com/images/thumbs/900x600/fit/2024/05/26/z5477018521570-a1b4f1c70125a3577e40bf3c2c26f514_1716705678.jpg",
                "https://pt123.cdn.static123.com/images/thumbs/900x600/fit/2024/05/26/z5477035161099-551b78c6a3f0ea43a6bedb0cb4d06817_1716705678.jpg",
                "https://pt123.cdn.static123.com/images/thumbs/900x600/fit/2024/05/26/z5477018493225-b1d0074d0391e9dd076d0b0161d77904_1716705676.jpg"
            ],
            "header": {
                "title": "Tin cá nhân đăng 4 giờ trước Tìm người ở ghép chung cư Becamex",
                "class": {
                    "content": "Chuyên mục: Tìm người ở ghép Thành phố Thuận An",
                    "clasType": "Tìm người ở ghép Thành phố Thuận An"
                },
                "address": "Địa chỉ: k2 D33, Phường An Phú, Thành phố Thuận An, Bình Dương",
                "attributes": {
                    "prices": "4.5 triệu/tháng",
                    "acreage": "51m2",
                    "published": "11 giờ trước",
                    "hashtag": "655764"
                }
            },
            "mainContent": {
                "header": "Thông tin mô tả",
                "content": [
                    "Mình là nhân viên văn phòng, cần tìm bạn nữ ở ghép sạch sẽ. Chung cư Becamex K2, an ninh tốt ngay vị trí trung tâm, gần KCN Vsip 1, Aeon mall Bình Dương.",
                    "Giá phòng 4.500.000 full nội thất đầy đủ, không thiếu gì.",
                    "Mong muốn tìm bạn nữ văn phòng ở lâu dài, hợp đồng đang thuê 1 năm. Thanks"
                ]
            },
            "overview": {
                "header": "Thông tin liên hệ",
                "content": [
                    {
                        "name": "Liên hệ:",
                        "content": "Hoang Hoa"
                    },
                    {
                        "name": "Điện thoại:",
                        "content": "0977374876"
                    },
                    {
                        "name": "Zalo",
                        "content": "0977374876"
                    }
                ]
            }
        },
        {
            "images": [
                "https://pt123.cdn.static123.com/images/thumbs/900x600/fit/2024/01/20/img-0735_1705717790.jpg",
                "https://pt123.cdn.static123.com/images/thumbs/900x600/fit/2024/01/20/img-0740_1705717778.jpg",
                "https://pt123.cdn.static123.com/images/thumbs/900x600/fit/2024/01/20/img-0737_1705717778.jpg",
                "https://pt123.cdn.static123.com/images/thumbs/900x600/fit/2024/01/20/img-0738_1705717784.jpg",
                "https://pt123.cdn.static123.com/images/thumbs/900x600/fit/2024/01/20/img-0739_1705717784.jpg",
                "https://pt123.cdn.static123.com/images/thumbs/900x600/fit/2024/01/20/img-0734_1705717789.jpg",
                "https://pt123.cdn.static123.com/images/thumbs/900x600/fit/2024/01/20/img-0735_1705717790.jpg",
                "https://pt123.cdn.static123.com/images/thumbs/900x600/fit/2024/01/20/img-0740_1705717778.jpg"
            ],
            "header": {
                "title": "Tìm bạn nữ ở ghép cùng 0338969794",
                "class": {
                    "content": "Chuyên mục: Tìm người ở ghép Quận Tân Bình",
                    "clasType": "Tìm người ở ghép Quận Tân Bình"
                },
                "address": "Địa chỉ: 41/5 Đường Mai Lão Bạng, Phường 13, Quận Tân Bình, Hồ Chí Minh",
                "attributes": {
                    "prices": "1 triệu/tháng",
                    "acreage": "30m2",
                    "published": "14 giờ trước",
                    "hashtag": "645925"
                }
            },
            "mainContent": {
                "header": "Thông tin mô tả",
                "content": [
                    "Hi xin chào, H đang ở 1 mình nên tìm bạn nữ nvvp nào có nhu cầu ở ghép cho đỡ chi phí. phòng sạch sẽ, thoáng mát, có ban công, tollet và có gác.",
                    "Giá phòng bao gồm tất cả là khoảng dưới 1tr5/1người.",
                    "Bạn nào có nhu cầu thì liên hệ mình theo sdt 0338969794 - Ngoc Hoa"
                ]
            },
            "overview": {
                "header": "Thông tin liên hệ",
                "content": [
                    {
                        "name": "Liên hệ:",
                        "content": "Pham Thi Ngoc Hoa"
                    },
                    {
                        "name": "Điện thoại:",
                        "content": "0338969794"
                    },
                    {
                        "name": "Zalo",
                        "content": "0338969794"
                    }
                ]
            }
        },
        {
            "images": [
                "https://pt123.cdn.static123.com/images/thumbs/900x600/fit/2024/04/15/img-20240415-225020_1713196866.jpg",
                "https://pt123.cdn.static123.com/images/thumbs/900x600/fit/2024/04/15/img-20240415-225054_1713196862.jpg",
                "https://pt123.cdn.static123.com/images/thumbs/900x600/fit/2024/04/15/img-20240415-225047_1713196861.jpg",
                "https://pt123.cdn.static123.com/images/thumbs/900x600/fit/2024/04/15/img-20240415-225039_1713196863.jpg",
                "https://pt123.cdn.static123.com/images/thumbs/900x600/fit/2024/04/15/img-20240415-225030_1713196865.jpg",
                "https://pt123.cdn.static123.com/images/thumbs/900x600/fit/2024/04/15/img-20240415-225020_1713196866.jpg",
                "https://pt123.cdn.static123.com/images/thumbs/900x600/fit/2024/04/15/img-20240415-225054_1713196862.jpg"
            ],
            "header": {
                "title": "cần share phòng cho bạn nam tại đường Vạn Kiếp",
                "class": {
                    "content": "Chuyên mục: Tìm người ở ghép Quận Bình Thạnh",
                    "clasType": "Tìm người ở ghép Quận Bình Thạnh"
                },
                "address": "Địa chỉ: Phố Vạn Kiếp, Phường 3, Quận Bình Thạnh, Hồ Chí Minh",
                "attributes": {
                    "prices": "2 triệu/tháng",
                    "acreage": "20m2",
                    "published": "15 giờ trước",
                    "hashtag": "652458"
                }
            },
            "mainContent": {
                "header": "Thông tin mô tả",
                "content": [
                    "- Cần share phòng cho bạn nam để giảm chi phí.",
                    "- Ngay khi ăn uống sầm uất.",
                    "- Phòng không chung chủ, có cả thang bộ và thang máy, máy giặt chung ở tầng hầm, cửa ra vào khóa vân tay.",
                    "- Phòng có máy lạnh, tủ lạnh, máy nước nóng lạnh, kệ bếp, tủ quần áo.",
                    "- Share phòng ngủ chung trên gác.",
                    "- Ghi chú: mình ngủ ngáy, bạn nào cùng cảnh ngộ thì xin mời.",
                    "- Giá share: 2tr."
                ]
            },
            "overview": {
                "header": "Thông tin liên hệ",
                "content": [
                    {
                        "name": "Liên hệ:",
                        "content": "Thanh Phong"
                    },
                    {
                        "name": "Điện thoại:",
                        "content": "0769721836"
                    },
                    {
                        "name": "Zalo",
                        "content": "0769721836"
                    }
                ]
            }
        },
        {
            "images": [
                "https://pt123.cdn.static123.com/images/thumbs/900x600/fit/2024/03/19/z5228565757669-a7e43db286b37b03a4f254189cfe02ae_1710807733.jpg",
                "https://pt123.cdn.static123.com/images/thumbs/900x600/fit/2024/03/19/phong-tro-3s_1710807680.jpg",
                "https://pt123.cdn.static123.com/images/thumbs/900x600/fit/2024/03/19/vi-tri-nha-tro-3s_1710807730.jpg",
                "https://pt123.cdn.static123.com/images/thumbs/900x600/fit/2024/03/19/z5228183733996-01673f36841351cc7395161b6abd824f_1710807730.jpg",
                "https://pt123.cdn.static123.com/images/thumbs/900x600/fit/2024/03/19/z5228183733997-920ad6ca60d60757f12c9c848d89fe24_1710807731.jpg",
                "https://pt123.cdn.static123.com/images/thumbs/900x600/fit/2024/03/19/z5228183751291-fdee351597da3c65a8acce1b5ba4fee1_1710807731.jpg",
                "https://pt123.cdn.static123.com/images/thumbs/900x600/fit/2024/03/19/z5228185312720-3d10e6d7259dad7ba193bc4f31066eee_1710807731.jpg",
                "https://pt123.cdn.static123.com/images/thumbs/900x600/fit/2024/03/19/z5228185313839-ef9294b4708f6261ca6add1ca6caf599_1710807731.jpg",
                "https://pt123.cdn.static123.com/images/thumbs/900x600/fit/2024/03/19/z5228185319520-1846e78baa70e4ed473ed428a0cbcd01_1710807732.jpg",
                "https://pt123.cdn.static123.com/images/thumbs/900x600/fit/2024/03/19/z5228185333112-5655ad725904a1b54bd28551ff033cf8_1710807732.jpg",
                "https://pt123.cdn.static123.com/images/thumbs/900x600/fit/2024/03/19/z5228185333175-07a708d11baeabf8dbca790df7016700_1710807733.jpg",
                "https://pt123.cdn.static123.com/images/thumbs/900x600/fit/2024/03/19/z5228565757669-a7e43db286b37b03a4f254189cfe02ae_1710807733.jpg",
                "https://pt123.cdn.static123.com/images/thumbs/900x600/fit/2024/03/19/phong-tro-3s_1710807680.jpg"
            ],
            "header": {
                "title": "Phòng trọ sinh viên, sleepbox Tân Phú, gần HUFI, đại học công thương Hồ Chí Minh",
                "class": {
                    "content": "Chuyên mục: Tìm người ở ghép Quận Tân Phú",
                    "clasType": "Tìm người ở ghép Quận Tân Phú"
                },
                "address": "Địa chỉ: 40/16/5 Đường số 27, Phường Sơn Kỳ, Quận Tân Phú, Hồ Chí Minh",
                "attributes": {
                    "prices": "1.2 triệu/tháng",
                    "acreage": "2.5m2",
                    "published": "1 ngày trước",
                    "hashtag": "649472"
                }
            },
            "mainContent": {
                "header": "Thông tin mô tả",
                "content": [
                    "Cho thuê KTX, Sleepbox, phòng trọ sinh viên, bao trọn gói chi phí gần HUFI",
                    "Cách ĐH công thương HCM 4 phút đi bộ",
                    "số 40/16/5 đường 27, phường Sơn Kỳ, quận Tân Phú",
                    "1tr/ th (phòng quạt). 1,3tr/ th (phòng máy lạnh).",
                    "bao gồm tất cả các tiện ích, không phát sinh thêm chi phí",
                    " ",
                    "Miễn phí 100% các dịnh vụ: Nước lọc, điện nước sinh hoạt, máy lạnh, máy giặt, bếp, chỗ để xe, sân phơi, dọn phòng ( thay grap nệm)",
                    "Không gian sinh hoạt riêng tư, mỗi box có ổ khóa, giá treo đồ, bàn học, đèn học và nguồn điện riêng",
                    "Giờ tự do, không chung chủ ",
                    "Liên hệ ngay ZALO: a.Thuận 0363097369",
                    "a.Phong 0326533342 - a.Tám 0918566128"
                ]
            },
            "overview": {
                "header": "Thông tin liên hệ",
                "content": [
                    {
                        "name": "Liên hệ:",
                        "content": "anh Tám"
                    },
                    {
                        "name": "Điện thoại:",
                        "content": "0902355766"
                    },
                    {
                        "name": "Zalo",
                        "content": "0902355766"
                    }
                ]
            }
        },
        {
            "images": [
                "https://pt123.cdn.static123.com/images/thumbs/900x600/fit/2024/05/01/z5398163452152-bf0e622741be8fdd2129f25b237701ad_1714536733.jpg",
                "https://pt123.cdn.static123.com/images/thumbs/900x600/fit/2024/05/01/z4437253953918-a410008fd9acb93a5ab0a593b07cefbd_1714536704.jpg",
                "https://pt123.cdn.static123.com/images/thumbs/900x600/fit/2024/05/01/z4437253997910-1228559f5d98a03a3c9b12a88034013f_1714536707.jpg",
                "https://pt123.cdn.static123.com/images/thumbs/900x600/fit/2024/05/01/z4437253978289-6682fed7e64225d9c872d5e02651b34e_1714536707.jpg",
                "https://pt123.cdn.static123.com/images/thumbs/900x600/fit/2024/05/01/nha-tro-thao-nguyen-xanh1_1714536725.jpg",
                "https://pt123.cdn.static123.com/images/thumbs/900x600/fit/2024/05/01/nha-tro-thao-nguyen-xanh3_1714536725.jpg",
                "https://pt123.cdn.static123.com/images/thumbs/900x600/fit/2024/05/01/nha-tro-thao-nguyen-xanh5_1714536728.jpg",
                "https://pt123.cdn.static123.com/images/thumbs/900x600/fit/2024/05/01/nha-tro-thao-nguyen-xanh6_1714536728.jpg",
                "https://pt123.cdn.static123.com/images/thumbs/900x600/fit/2024/05/01/z5398163439776-090d948eb75e3434678261acc84b0aa9_1714536730.jpg",
                "https://pt123.cdn.static123.com/images/thumbs/900x600/fit/2024/05/01/z5398163449822-91f8ff42b4a4944c4f7bda040a05e0a1_1714536731.jpg",
                "https://pt123.cdn.static123.com/images/thumbs/900x600/fit/2024/05/01/z5398163452152-bf0e622741be8fdd2129f25b237701ad_1714536733.jpg",
                "https://pt123.cdn.static123.com/images/thumbs/900x600/fit/2024/05/01/z4437253953918-a410008fd9acb93a5ab0a593b07cefbd_1714536704.jpg"
            ],
            "header": {
                "title": "PHÒNG 4 BẠN NGAY CÁC TRƯỜNG ĐẠI HỌC TRÊN LÊ VĂN VIỆT chỉ 1 Triệu",
                "class": {
                    "content": "Chuyên mục: Tìm người ở ghép Quận 9",
                    "clasType": "Tìm người ở ghép Quận 9"
                },
                "address": "Địa chỉ: Làng Tăng Phú, Phường Tăng Nhơn Phú A, Quận 9, Hồ Chí Minh",
                "attributes": {
                    "prices": "1.3 triệu/tháng",
                    "acreage": "30m2",
                    "published": "1 ngày trước",
                    "hashtag": "653693"
                }
            },
            "mainContent": {
                "header": "Thông tin mô tả",
                "content": [
                    "PHÒNG 4 BẠN NGAY CÁC TRƯỜNG ĐẠI HỌC TRÊN LÊ VĂN VIỆT",
                    "~ Giá chỉ 1,3 triệu ( PHÒNG 4 -6 BẠN )",
                    "~ Địa chỉ: 74B đường Làng Tăng Phú. Phường Tăng Nhơn Phú A. TP Thủ Đức.",
                    "LIÊN HỆ SỐ ZALO 0908076490 để được tư vấn trực tiếp và cụ thể hơn nhé.",
                    "Phòng ở ghép dành cho các bạn Nam gần ngay các trường ĐH TC MKT - HUTECH - FPT - GTVT - LÊ VĂN VIỆT",
                    "PHÒNG ĐẦY ĐỦ NỘI THẤT - MÁY LẠNH 24/24:",
                    "Phòng mới setup 100%, hoàn toàn mới.",
                    "Máy lạnh hoạt động 24/24, giữ không khí mát mẻ.",
                    "Rèm che từng giường, đảm bảo không gian riêng tư.",
                    "Tủ đựng quần áo siêu rộng.",
                    "BẾP ĂN RIÊNG BIỆT - ĐẦY ĐỦ TIỆN NGHI:",
                    "Bếp từ và đầy đủ dụng cụ nấu ăn.",
                    "Bàn ăn tiện lợi.",
                    "Tủ lạnh và máy lọc nước.",
                    "Tủ đựng đồ gia vị đầy đủ.",
                    "LIÊN HỆ ĐẶT PHÒNG NGAY HÔM NAY:",
                    "Số điện thoại: [0908076490]"
                ]
            },
            "overview": {
                "header": "Thông tin liên hệ",
                "content": [
                    {
                        "name": "Liên hệ:",
                        "content": "nguyễn ngọc lan hương"
                    },
                    {
                        "name": "Điện thoại:",
                        "content": "0908076490"
                    },
                    {
                        "name": "Zalo",
                        "content": "0908076490"
                    }
                ]
            }
        },
        {
            "images": [],
            "header": {
                "title": "Cần tìm nữ ở ghép gấp, chung cư 86 Nguyễn Thông, Quận 3",
                "class": {
                    "content": "Chuyên mục: Tìm người ở ghép Quận 3",
                    "clasType": "Tìm người ở ghép Quận 3"
                },
                "address": "Địa chỉ: 86 Đường Nguyễn Thông, Phường 9, Quận 3, Hồ Chí Minh",
                "attributes": {
                    "prices": "700.000 đồng/tháng",
                    "acreage": "30m2",
                    "published": "1 ngày trước",
                    "hashtag": "129272"
                }
            },
            "mainContent": {
                "header": "Thông tin mô tả",
                "content": [
                    "CẦN TÌM NỮ Ở GHÉP GẤP 700k/ tháng",
                    "Nhà nguyên căn sạch sẽ, thoáng mát, gần chợ, gần ga Sài Gòn, trung tâm Quận 3 , chìa khóa riêng",
                    "Gía 700k/tháng bao điện nước, Cần nử sinh viên ,",
                    "nhân viên văn phòng hoặc có việc làm ổn định",
                    "Liên hệ: cô My - số điện thoại: 0908977952"
                ]
            },
            "overview": {
                "header": "Thông tin liên hệ",
                "content": [
                    {
                        "name": "Liên hệ:",
                        "content": "thailuong2015"
                    },
                    {
                        "name": "Điện thoại:",
                        "content": "0908977952"
                    },
                    {
                        "name": "Zalo",
                        "content": "0908977952"
                    }
                ]
            }
        },
        {
            "images": [
                "https://pt123.cdn.static123.com/images/thumbs/900x600/fit/2024/02/24/4_1708776260.jpg",
                "https://pt123.cdn.static123.com/images/thumbs/900x600/fit/2024/02/24/1_1708776258.jpg",
                "https://pt123.cdn.static123.com/images/thumbs/900x600/fit/2024/02/24/2_1708776258.jpg",
                "https://pt123.cdn.static123.com/images/thumbs/900x600/fit/2024/02/24/3_1708776260.jpg",
                "https://pt123.cdn.static123.com/images/thumbs/900x600/fit/2024/02/24/4_1708776260.jpg",
                "https://pt123.cdn.static123.com/images/thumbs/900x600/fit/2024/02/24/1_1708776258.jpg"
            ],
            "header": {
                "title": "Ký Túc Xá Giá Rẻ KDC Nam Long Quận 9",
                "class": {
                    "content": "Chuyên mục: Tìm người ở ghép Quận 9",
                    "clasType": "Tìm người ở ghép Quận 9"
                },
                "address": "Địa chỉ: Đường Đỗ Xuân Hợp, Phường Long Phước, Quận 9, Hồ Chí Minh",
                "attributes": {
                    "prices": "1 triệu/tháng",
                    "acreage": "120m2",
                    "published": "2 ngày trước",
                    "hashtag": "301430"
                }
            },
            "mainContent": {
                "header": "Thông tin mô tả",
                "content": [
                    "KÝ TÚC XÁ GIÁ RẺ PHƯỚC LONG B QUẬN 9",
                    "️Địa Chỉ: Khu Dân Cư Nam Long, Phường Phước Long B, Quận 9.",
                    "Cách Quận 1: 15 Phút Đi Xe Máy.",
                    "Gần Nút Giao Đỗ Xuân Hợp Và Liên Phường, Khu Công Nghệ Cao, Trường Cao Đẳng Kinh Tế Đối Ngoại, Đại Học Văn Hóa.",
                    "️Nội Thất",
                    "Giường Tầng.",
                    "Máy Lạnh.",
                    "Tủ Lạnh, Bếp Từ, Lò Vi Sóng, Nội Thất Bếp.",
                    "Máy Giặt, Sân Phơi Đồ. - Tủ Quần Áo, Bàn Làm Việc.",
                    "️Tiện Ích",
                    "Môi Trường Sống Tiện Nghi",
                    "Các Cửa Hàng Tiện Lợi, Bách Hóa Xanh, Quán Ăn, Cà Phê.",
                    "Sân Bóng Chuyền, Công Viên Cây Xanh.",
                    "️Khách Hàng",
                    "Khách Hàng Của Chúng Tôi Là Những Nhân Viên Văn Phòng, Sinh Viên Đại Học, Người Đi Làm Có Văn Hóa, Ý Thức Để Cùng Nhau Xây Dựng Một Môi Trường Sống Văn Minh Tiện Lợi Với Mức Giá Hợp Lý.",
                    "️Liên Hệ: 0363096032"
                ]
            },
            "overview": {
                "header": "Thông tin liên hệ",
                "content": [
                    {
                        "name": "Liên hệ:",
                        "content": "Bùi Lê Tố Quyên"
                    },
                    {
                        "name": "Điện thoại:",
                        "content": "0363096032"
                    },
                    {
                        "name": "Zalo",
                        "content": "0363096032"
                    }
                ]
            }
        },
        {
            "images": [
                "https://pt123.cdn.static123.com/images/thumbs/900x600/fit/2024/05/24/img-20240503-141458-986_1716510035.jpg",
                "https://pt123.cdn.static123.com/images/thumbs/900x600/fit/2024/05/24/img-20240503-131502-949_1716509952.jpg",
                "https://pt123.cdn.static123.com/images/thumbs/900x600/fit/2024/05/24/img-20240503-141319-039_1716509970.jpg",
                "https://pt123.cdn.static123.com/images/thumbs/900x600/fit/2024/05/24/img-20240503-141634-815_1716509987.jpg",
                "https://pt123.cdn.static123.com/images/thumbs/900x600/fit/2024/05/24/img-20240503-141626-718_1716510002.jpg",
                "https://pt123.cdn.static123.com/images/thumbs/900x600/fit/2024/05/24/img-20240503-141422-049_1716510010.jpg",
                "https://pt123.cdn.static123.com/images/thumbs/900x600/fit/2024/05/24/img-20240503-141458-986_1716510035.jpg",
                "https://pt123.cdn.static123.com/images/thumbs/900x600/fit/2024/05/24/img-20240503-131502-949_1716509952.jpg"
            ],
            "header": {
                "title": "Tìm người ở ghép căn hộ chung cư Lê Thành Tân Tạo 33,9m tháng 800k quận Bình Tân",
                "class": {
                    "content": "Chuyên mục: Tìm người ở ghép Quận Bình Tân",
                    "clasType": "Tìm người ở ghép Quận Bình Tân"
                },
                "address": "Địa chỉ: Đường Hồ Văn Long, Phường Tân Tạo, Quận Bình Tân, Hồ Chí Minh",
                "attributes": {
                    "prices": "1.2 triệu/tháng",
                    "acreage": "33.9m2",
                    "published": "2 ngày trước",
                    "hashtag": "655591"
                }
            },
            "mainContent": {
                "header": "Thông tin mô tả",
                "content": [
                    "Tìm người ở ghép căn hộ chung cư Lê Thành Tân Tạo đường Hồ Văn Long, phường Tân Tạo, quận Bình Tân HCM.",
                    "Tháng đầu 800nghìn. Tiền điện, nước chia đều cho mỗi bên.",
                    "Cho phép nấu ăn trong phòng.",
                    "Phòng còn mới trống chưa có người ở.",
                    "Liên hệ Đoan Trang 0777359101",
                    " "
                ]
            },
            "overview": {
                "header": "Thông tin liên hệ",
                "content": [
                    {
                        "name": "Liên hệ:",
                        "content": "Phạm Lê Đoan Trang"
                    },
                    {
                        "name": "Điện thoại:",
                        "content": "0777359101"
                    },
                    {
                        "name": "Zalo",
                        "content": "0777359101"
                    }
                ]
            }
        },
        {
            "images": [],
            "header": {
                "title": "CẦN TÌM MỘT BẠN NỮ SINH VIÊN HOẶC ĐI LÀM Ở GHÉP",
                "class": {
                    "content": "Chuyên mục: Tìm người ở ghép Quận Tân Phú",
                    "clasType": "Tìm người ở ghép Quận Tân Phú"
                },
                "address": "Địa chỉ: 11/25A Dương Đức Hiền, Phường Tây Thạnh, Quận Tân Phú, Hồ Chí Minh",
                "attributes": {
                    "prices": "1.2 triệu/tháng",
                    "acreage": "20m2",
                    "published": "3 ngày trước",
                    "hashtag": "655555"
                }
            },
            "mainContent": {
                "header": "Thông tin mô tả",
                "content": [
                    "Cần tìm một bạn nữ đi học hoặc đi làm ở ghép.",
                    "Nhà đầy đủ tiện nghi máy giặt, tủ lạnh, bàn máy tính, có gác lửng",
                    "Gần trường đại học công thương",
                    "Gần siêu thị",
                    "Nhà trọ 11h đóng cửa. Cần người ở sạch sẽ thiện chí ở lâu dài.",
                    "Tiền nhà : 1tr2/ người ( chưa bao gồm điện nước )"
                ]
            },
            "overview": {
                "header": "Thông tin liên hệ",
                "content": [
                    {
                        "name": "Liên hệ:",
                        "content": "Vo thi minh phuong"
                    },
                    {
                        "name": "Điện thoại:",
                        "content": "0907096707"
                    },
                    {
                        "name": "Zalo",
                        "content": "0907096707"
                    }
                ]
            }
        }
    ]
}